slangtorch/__init__.py
slangtorch/slangtorch.py
slangtorch/bin/libslang-compiler.so.0.2025.23.2
slangtorch/bin/libslang-glsl-module-2025.23.2.so
slangtorch/bin/slang-compiler.dll
slangtorch/bin/slang-glsl-module.dll
slangtorch/bin/slangc
slangtorch/bin/slangc.exe
slangtorch/util/__init__.py
slangtorch/util/builtin_wrappers.py
slangtorch/util/compile.py
slangtorch/util/wrapper.py
slangtorch-1.3.18.dist-info/METADATA
slangtorch-1.3.18.dist-info/WHEEL
slangtorch-1.3.18.dist-info/licenses/LICENSE
slangtorch-1.3.18.dist-info/RECORD
